coil/__init__.py
coil/__main__.py
coil/forms.py
coil/init.py
coil/tasks.py
coil/utils.py
coil/web.py
coil/data/bower_components/wysihtml/.bower.json
coil/data/bower_components/wysihtml/CHANGELOG.textile
coil/data/bower_components/wysihtml/Gruntfile.js
coil/data/bower_components/wysihtml/LICENSE
coil/data/bower_components/wysihtml/README.markdown
coil/data/bower_components/wysihtml/bower.json
coil/data/bower_components/wysihtml/package.json
coil/data/bower_components/wysihtml/dist/wysihtml5x-toolbar.js
coil/data/bower_components/wysihtml/dist/wysihtml5x-toolbar.min.js
coil/data/bower_components/wysihtml/dist/wysihtml5x-toolbar.min.map
coil/data/bower_components/wysihtml/dist/wysihtml5x.js
coil/data/bower_components/wysihtml/dist/wysihtml5x.min.js
coil/data/bower_components/wysihtml/dist/wysihtml5x.min.map
coil/data/bower_components/wysihtml/lib/base/base.js
coil/data/bower_components/wysihtml/parser_rules/advanced.js
coil/data/bower_components/wysihtml/parser_rules/advanced_and_extended.js
coil/data/bower_components/wysihtml/parser_rules/advanced_unwrap.js
coil/data/bower_components/wysihtml/parser_rules/simple.js
coil/data/coil_assets/css/coil.css
coil/data/coil_assets/css/wysihtml5x.css
coil/data/coil_assets/js/coil.js
coil/data/templates/convert.py
coil/data/templates/jinja/coil_account.tmpl
coil/data/templates/jinja/coil_account_single.tmpl
coil/data/templates/jinja/coil_error.tmpl
coil/data/templates/jinja/coil_index.tmpl
coil/data/templates/jinja/coil_login.tmpl
coil/data/templates/jinja/coil_post_edit.tmpl
coil/data/templates/jinja/coil_pwdhash.tmpl
coil/data/templates/jinja/coil_rebuild.tmpl
coil/data/templates/jinja/coil_rebuild_single.tmpl
coil/data/templates/jinja/coil_users.tmpl
coil/data/templates/jinja/coil_users_edit.tmpl
coil/data/templates/jinja/coil_users_permissions.tmpl
coil/data/templates/mako/coil_account.tmpl
coil/data/templates/mako/coil_account_single.tmpl
coil/data/templates/mako/coil_error.tmpl
coil-1.3.12.dist-info/DESCRIPTION.rst
coil-1.3.12.dist-info/METADATA
coil-1.3.12.dist-info/RECORD
coil-1.3.12.dist-info/WHEEL
coil-1.3.12.dist-info/entry_points.txt
coil-1.3.12.dist-info/metadata.json
coil-1.3.12.dist-info/top_level.txt
