Metadata-Version: 2.0
Name: coil
Version: 1.3.12
Summary: A user-friendly CMS frontend for Nikola.
Home-page: https://github.com/getnikola/coil
Author: Chris Warrick, Roberto Alsina, Henry Hirsch et al.
Author-email: chris@getnikola.com
License: MIT
Keywords: coil,nikola,cms
Platform: any
Classifier: Development Status :: 7 - Inactive
Classifier: Programming Language :: Python
Classifier: Programming Language :: Python :: 3
Classifier: Programming Language :: Python :: 3.3
Classifier: Programming Language :: Python :: 3.4
Classifier: Programming Language :: Python :: 3.5
Classifier: Programming Language :: Python :: 3.6
Requires-Dist: Flask (==0.10.1)
Requires-Dist: Flask-Bcrypt (==0.6.2)
Requires-Dist: Flask-Login (==0.2.11)
Requires-Dist: Flask-WTF (==0.12)
Requires-Dist: Logbook (==0.10.1)
Requires-Dist: Nikola (>=7.6.4)
Requires-Dist: WTForms (==2.0.2)
Requires-Dist: docopt (==0.6.2)
Requires-Dist: passlib (==1.6.5)
Requires-Dist: py-bcrypt (==0.4)
Requires-Dist: python-bcrypt (==0.3.1)
Requires-Dist: redis (==2.10.3)
Requires-Dist: requests (==2.7.0)
Requires-Dist: rq (==0.5.5)
Requires-Dist: webassets (==0.11.1)
